rcv_cruncher/.DS_Store
rcv_cruncher/WIPDevcode.py
rcv_cruncher/__init__.py
rcv_cruncher/__main__.py
rcv_cruncher/batch.py
rcv_cruncher/cli.py
rcv_cruncher/contest_set_settings.json
rcv_cruncher/marks.py
rcv_cruncher/parsers.py
rcv_cruncher/run_config_settings.json
rcv_cruncher/util.py
rcv_cruncher/cvr/base.py
rcv_cruncher/cvr/stats.py
rcv_cruncher/cvr/tables.py
rcv_cruncher/example/.DS_Store
rcv_cruncher/example/contest_sets/.DS_Store
rcv_cruncher/example/contest_sets/example/contest_set.csv
rcv_cruncher/example/contest_sets/example/run_config.json
rcv_cruncher/example/example_cvr/.DS_Store
rcv_cruncher/example/example_cvr/minneapolis2017/2017-boe-cvr.csv
rcv_cruncher/example/example_cvr/minneapolis2017/2017-mayor-cvr.csv
rcv_cruncher/example/example_cvr/minneapolis2017/2017-park-at-large-cvr.csv
rcv_cruncher/example/example_cvr/minneapolis2017/2017-park-district-4-cvr.csv
rcv_cruncher/example/example_cvr/minneapolis2017/2017-park-district-5-cvr.csv
rcv_cruncher/example/example_cvr/minneapolis2017/2017-ward-9-cvr.csv
rcv_cruncher/example/test_docs/.DS_Store
rcv_cruncher/example/test_docs/parse_convert.py
rcv_cruncher/example/test_docs/tabulation.py
rcv_cruncher/example/test_docs/tabulation_bottomsup.py
rcv_cruncher/example/test_docs/parse_convert/.DS_Store
rcv_cruncher/example/test_docs/parse_convert/output/.DS_Store
rcv_cruncher/example/test_docs/parse_convert/output/candidate_format/.DS_Store
rcv_cruncher/example/test_docs/parse_convert/output/candidate_format/Minneapolis_2017_Mayor.csv
rcv_cruncher/example/test_docs/parse_convert/output/rank_format/.DS_Store
rcv_cruncher/example/test_docs/parse_convert/output/rank_format/Minneapolis_2017_Mayor.csv
rcv_cruncher/example/test_docs/tabulation/.DS_Store
rcv_cruncher/example/test_docs/tabulation/round_by_round_json/Minneapolis_2017_BoardofEstimatesandTaxation_tab1.json
rcv_cruncher/example/test_docs/tabulation/round_by_round_json/Minneapolis_2017_Mayor_tab1.json
rcv_cruncher-0.0.16.dist-info/METADATA
rcv_cruncher-0.0.16.dist-info/WHEEL
rcv_cruncher-0.0.16.dist-info/entry_points.txt
rcv_cruncher-0.0.16.dist-info/top_level.txt
rcv_cruncher-0.0.16.dist-info/RECORD
